setup.cfg
setup.py
movielens_retriever/__init__.py
movielens_retriever/data.py
movielens_retriever.egg-info/PKG-INFO
movielens_retriever.egg-info/SOURCES.txt
movielens_retriever.egg-info/dependency_links.txt
movielens_retriever.egg-info/top_level.txt
test/__init__.py
test/test.py