Metadata-Version: 1.1
Name: movielens-retriever
Version: 0.11
Summary: A package to download movielens dataset and create interactions matrices
Home-page: https://github.com/datrik/movielens_retrivever
Author: Datrik Intelligence, S.A.
Author-email: info@datrik.com
License: MIT
Download-URL: https://github.com/datrik/movielens_retrivever/tarball/0.11
Keywords: datrik movielens dataset interaction matrix
Platform: UNKNOWN
Classifier: Operating System :: OS Independent
Classifier: Programming Language :: Python
Classifier: Topic :: Software Development :: Libraries :: Python Modules
